ssi4onnx/__init__.py
ssi4onnx/__main__.py
ssi4onnx/onnx_shape_inference.py
ssi4onnx-1.0.4.dist-info/LICENSE
ssi4onnx-1.0.4.dist-info/METADATA
ssi4onnx-1.0.4.dist-info/WHEEL
ssi4onnx-1.0.4.dist-info/entry_points.txt
ssi4onnx-1.0.4.dist-info/top_level.txt
ssi4onnx-1.0.4.dist-info/RECORD
