Metadata-Version: 2.1
Name: ssi4onnx
Version: 1.0.4
Summary: Simple Shape Inference tool for ONNX.
Home-page: https://github.com/PINTO0309/ssi4onnx
Author: Katsuya Hyodo
Author-email: rmsdh122@yahoo.co.jp
License: MIT License
Platform: linux
Platform: unix
Requires-Python: >=3.6
License-File: LICENSE
